{"content":"The White Stripes","description":"2 / Rock"}
{"content":"Kendrick Lamar","description":"1 / Hip-Hop"}
{"content":"The Kills","description":"2 / Rock"}
{"content":"Arctic Monkeys","description":"4 / Rock"}
{"content":"Orelha Negra","description":"5 / Hip-Hop"}
{"content":"Miles Davis","description":"1 / Jazz"}
{"content":"Queens Of The Stone Age","description":"5 / Rock"}
{"content":"Beck","description":"1 / Alternative"}
{"content":"Lorde","description":"1 / Pop"}
{"content":"The Raconteurs","description":"4 / Rock"}
{"content":"Bob Dylan","description":"1 / Folk"}
{"content":"Iggy Pop","description":"1 / Punk"}
{"content":"Royal Blood","description":"2 / Rock"}
{"content":"The Black Keys","description":"2 / Rock"}
{"content":"The Dead Weather","description":"4 / Rock"}